ukw_fax/__init__.py
ukw_fax/__main__.py
ukw_fax/cli.py
ukw_fax/utils.py
ukw_fax-0.0.2.dist-info/AUTHORS.rst
ukw_fax-0.0.2.dist-info/LICENSE
ukw_fax-0.0.2.dist-info/METADATA
ukw_fax-0.0.2.dist-info/WHEEL
ukw_fax-0.0.2.dist-info/entry_points.txt
ukw_fax-0.0.2.dist-info/top_level.txt
ukw_fax-0.0.2.dist-info/RECORD
