Metadata-Version: 2.1
Name: ukw-fax
Version: 0.0.2
Summary: Package to read outlook mails and extract attached .tifs to fspecific folder structure.
Home-page: https://github.com/Maddonix/ukw_fax
Author: Thomas J. Lux
Author-email: tlux14@gmail.com
License: MIT
Project-URL: Documentation, https://ukw_fax.readthedocs.io/
Project-URL: Changelog, https://ukw_fax.readthedocs.io/en/latest/changelog.html
Project-URL: Issue Tracker, https://github.com/Maddonix/ukw_fax/issues
Platform: UNKNOWN
Classifier: Development Status :: 5 - Production/Stable
Classifier: Intended Audience :: Developers
Classifier: License :: OSI Approved :: MIT License
Classifier: Operating System :: Unix
Classifier: Operating System :: POSIX
Classifier: Operating System :: Microsoft :: Windows
Classifier: Programming Language :: Python
Classifier: Programming Language :: Python :: 3
Classifier: Programming Language :: Python :: 3 :: Only
Classifier: Programming Language :: Python :: 3.6
Classifier: Programming Language :: Python :: 3.7
Classifier: Programming Language :: Python :: 3.8
Classifier: Programming Language :: Python :: 3.9
Classifier: Programming Language :: Python :: Implementation :: CPython
Classifier: Programming Language :: Python :: Implementation :: PyPy
Classifier: Topic :: Utilities
Requires-Python: >=3.6
Requires-Dist: pytest
Requires-Dist: tqdm
Requires-Dist: pytesseract
Requires-Dist: mail-parser
